[
  {
    "name": "Azores · Policy & Regional",
    "sources": [
      { "label": "Governo dos Açores", "url": "https://www.azores.gov.pt/pt" },
      { "label": "Diário da República", "url": "https://dre.pt/web/guest/home" },
      { "label": "INOVA (Inovação Açores)", "url": "https://inova.azores.gov.pt" }
    ]
  },
  {
    "name": "São Miguel · Environment & Research",
    "sources": [
      { "label": "Azores Geopark", "url": "https://azoresgeopark.com" },
      { "label": "Universidade dos Açores", "url": "https://www.uac.pt" },
      { "label": "Nature/Science (Azores)", "url": "https://www.nature.com/subjects/island-biology" }
    ]
  },
  {
    "name": "Permaculture & Regeneration",
    "sources": [
      { "label": "FAO Agroecology", "url": "https://www.fao.org/agroecology/en/" },
      { "label": "Regeneration.org", "url": "https://regeneration.org/" },
      { "label": "EU Environment", "url": "https://environment.ec.europa.eu/news_en?format=rss" }
    ]
  },
  {
    "name": "YouTube Channels",
    "sources": [
      { "label": "@DiscoverPermaculture", "url": "https://www.youtube.com/@DiscoverPermaculture" },
      { "label": "@amillison", "url": "https://www.youtube.com/@amillison" }
    ]
  }
]
